casechecking/__init__.py
casechecking/boundaries.py
casechecking/camel.py
casechecking/camel_test.py
casechecking/casechecking.py
casechecking/casechecking_test.py
casechecking/cobol.py
casechecking/cobol_test.py
casechecking/flat.py
casechecking/flat_test.py
casechecking/kebab.py
casechecking/kebab_test.py
casechecking/macro.py
casechecking/macro_test.py
casechecking/pascal.py
casechecking/pascal_test.py
casechecking/snake.py
casechecking/snake_test.py
casechecking/adt/basedu.py
casechecking-0.0.8.dist-info/METADATA
casechecking-0.0.8.dist-info/WHEEL
casechecking-0.0.8.dist-info/licenses/LICENSE
casechecking-0.0.8.dist-info/RECORD
