Metadata-Version: 2.1
Name: casechecking
Version: 0.0.8
Summary: OS Information Package
Project-URL: Homepage, https://github.com/casechecking/casechecking
Project-URL: Bug Tracker, https://github.com/casechecking/casechecking/issues
Author-email: Mriana Camelia <casechecking@gmail.com>
License-File: LICENSE
Classifier: License :: OSI Approved :: MIT License
Classifier: Operating System :: OS Independent
Classifier: Programming Language :: Python :: 3
Requires-Python: >=3.7
